webexintegration/__init__.py
webexintegration/webex_formatter.py
webexintegration/webex_teams.py
webexintegration/webex_teams_handler.py
webex_integration-0.0.3.dist-info/LICENSE
webex_integration-0.0.3.dist-info/METADATA
webex_integration-0.0.3.dist-info/WHEEL
webex_integration-0.0.3.dist-info/top_level.txt
webex_integration-0.0.3.dist-info/RECORD
