Metadata-Version: 2.1
Name: webex-integration
Version: 0.0.3
Summary: integrate Webex to your python project
Author: Deutsche Telekom IT GmbH
License: Apache Software License (Apache 2.0)
Keywords: python,webex,logging,chat,cisco
Classifier: Intended Audience :: Developers
Classifier: Programming Language :: Python :: 3
Classifier: License :: OSI Approved :: Apache Software License
Classifier: Natural Language :: English
Classifier: Operating System :: OS Independent
Classifier: Development Status :: 4 - Beta
License-File: LICENSE
Requires-Dist: requests
